{"file":"achievement_task.png","frames":{
"CH-1":{"x":881,"y":420,"w":113,"h":58,"offX":0,"offY":0,"sourceW":113,"sourceH":58},
"CH-2da":{"x":985,"y":1,"w":34,"h":37,"offX":0,"offY":0,"sourceW":34,"sourceH":37},
"CH-3da":{"x":603,"y":139,"w":34,"h":37,"offX":0,"offY":0,"sourceW":34,"sourceH":37},
"CH-4xiao":{"x":639,"y":139,"w":28,"h":32,"offX":0,"offY":0,"sourceW":28,"sourceH":32},
"CH-5xiao":{"x":664,"y":467,"w":28,"h":32,"offX":0,"offY":0,"sourceW":28,"sourceH":32},
"CH-6":{"x":873,"y":480,"w":115,"h":25,"offX":0,"offY":0,"sourceW":115,"sourceH":25},
"CH-7":{"x":547,"y":467,"w":115,"h":25,"offX":0,"offY":0,"sourceW":115,"sourceH":25},
"CH-8":{"x":881,"y":359,"w":132,"h":59,"offX":0,"offY":0,"sourceW":132,"sourceH":59},
"CH-9":{"x":674,"y":120,"w":90,"h":29,"offX":0,"offY":0,"sourceW":90,"sourceH":29},
"CH-10":{"x":674,"y":70,"w":81,"h":48,"offX":0,"offY":0,"sourceW":81,"sourceH":48},
"CH-11":{"x":461,"y":359,"w":300,"h":54,"offX":0,"offY":0,"sourceW":300,"sourceH":54},
"CH-12":{"x":1,"y":1,"w":458,"h":458,"offX":0,"offY":0,"sourceW":458,"sourceH":458},
"CH-13":{"x":547,"y":508,"w":191,"h":1,"offX":0,"offY":0,"sourceW":191,"sourceH":1},
"everday_1":{"x":603,"y":1,"w":69,"h":67,"offX":0,"offY":0,"sourceW":69,"sourceH":67},
"everday_2":{"x":674,"y":1,"w":69,"h":67,"offX":0,"offY":0,"sourceW":69,"sourceH":67},
"everday_3":{"x":843,"y":1,"w":69,"h":67,"offX":0,"offY":0,"sourceW":69,"sourceH":67},
"everday_4":{"x":914,"y":1,"w":69,"h":67,"offX":0,"offY":0,"sourceW":69,"sourceH":67},
"everday_5":{"x":772,"y":70,"w":69,"h":67,"offX":0,"offY":0,"sourceW":69,"sourceH":67},
"everday_6":{"x":603,"y":70,"w":69,"h":67,"offX":0,"offY":0,"sourceW":69,"sourceH":67},
"everday_7":{"x":802,"y":439,"w":69,"h":67,"offX":0,"offY":0,"sourceW":69,"sourceH":67},
"everday_8":{"x":772,"y":1,"w":69,"h":67,"offX":0,"offY":0,"sourceW":69,"sourceH":67},
"MRRW_03":{"x":547,"y":415,"w":145,"h":50,"offX":0,"offY":0,"sourceW":145,"sourceH":50},
"MRRW_07":{"x":461,"y":1,"w":140,"h":263,"offX":0,"offY":0,"sourceW":140,"sourceH":263},
"MRRW_10":{"x":694,"y":439,"w":106,"h":52,"offX":0,"offY":0,"sourceW":106,"sourceH":52},
"MRRW_14":{"x":763,"y":359,"w":116,"h":78,"offX":0,"offY":0,"sourceW":116,"sourceH":78},
"MRRW_24":{"x":461,"y":415,"w":84,"h":93,"offX":0,"offY":0,"sourceW":84,"sourceH":93},
"NPC_03":{"x":461,"y":266,"w":309,"h":91,"offX":0,"offY":0,"sourceW":309,"sourceH":91},
"NPC_07":{"x":1,"y":461,"w":86,"h":28,"offX":0,"offY":0,"sourceW":86,"sourceH":28},
"NPC_11":{"x":89,"y":461,"w":70,"h":25,"offX":0,"offY":0,"sourceW":70,"sourceH":25},
"CJ-yueliang1":{"x":990,"y":480,"w":25,"h":25,"offX":0,"offY":0,"sourceW":25,"sourceH":25},
"CJ-yueliang2":{"x":996,"y":420,"w":25,"h":25,"offX":0,"offY":0,"sourceW":25,"sourceH":25}}}